./.gitignore
./LICENSE
./PKG-INFO
./README.md
./config.json
./pyproject.toml
./requirements.txt
./server.py
cloud_mcp_libro-1.0.4.dist-info/METADATA
cloud_mcp_libro-1.0.4.dist-info/WHEEL
cloud_mcp_libro-1.0.4.dist-info/entry_points.txt
cloud_mcp_libro-1.0.4.dist-info/licenses/LICENSE
cloud_mcp_libro-1.0.4.dist-info/RECORD
