Metadata-Version: 2.4
Name: cloud-mcp-libro
Version: 1.0.4
Summary: Cloud Platform MCP Server - Provides access to backend APIs through MCP protocol
Project-URL: Homepage, https://github.com/DesignLibro/cloud-mcp-libro
Project-URL: Repository, https://github.com/DesignLibro/cloud-mcp-libro
Project-URL: Issues, https://github.com/DesignLibro/cloud-mcp-libro/issues
Project-URL: Documentation, https://github.com/DesignLibro/cloud-mcp-libro/blob/master/README.md
Project-URL: Changelog, https://github.com/DesignLibro/cloud-mcp-libro/releases
Author-email: limo <limo.yu@designlibro.com>
Maintainer-email: limo <limo.yu@designlibro.com>
License: MIT License
License-File: LICENSE
Keywords: ai,api,assistant,cloud,mcp,protocol,server
Classifier: Development Status :: 4 - Beta
Classifier: Intended Audience :: Developers
Classifier: License :: OSI Approved :: MIT License
Classifier: Programming Language :: Python :: 3
Classifier: Programming Language :: Python :: 3.8
Classifier: Programming Language :: Python :: 3.9
Classifier: Programming Language :: Python :: 3.10
Classifier: Programming Language :: Python :: 3.11
Classifier: Programming Language :: Python :: 3.12
Classifier: Topic :: Internet :: WWW/HTTP :: HTTP Servers
Classifier: Topic :: Software Development :: Libraries :: Python Modules
Classifier: Topic :: System :: Networking
Requires-Python: >=3.8
Requires-Dist: aiohttp>=3.9.0
Requires-Dist: mcp>=1.0.0
Requires-Dist: pydantic>=2.0.0
Provides-Extra: dev
Requires-Dist: pytest-asyncio>=0.21.0; extra == 'dev'
Requires-Dist: pytest-cov>=4.0.0; extra == 'dev'
Requires-Dist: pytest>=7.0.0; extra == 'dev'
Provides-Extra: test
Requires-Dist: pytest-asyncio>=0.21.0; extra == 'test'
Requires-Dist: pytest>=7.0.0; extra == 'test'
